pyspecdenoise/__init__.py
pyspecdenoise/fourier.py
pyspecdenoise-1.0.4.dist-info/LICENSE
pyspecdenoise-1.0.4.dist-info/METADATA
pyspecdenoise-1.0.4.dist-info/WHEEL
pyspecdenoise-1.0.4.dist-info/top_level.txt
pyspecdenoise-1.0.4.dist-info/RECORD
