Metadata-Version: 2.1
Name: pyspecdenoise
Version: 1.0.4
Summary: Perform Fourier de-noising of supernova spectra (Liu et al., 2016). Follows Finneran et al. (2024). See: https://arxiv.org/abs/2411.12574.
Author-email: Gabriel Finneran <gabfin15@gmail.com>
Project-URL: Homepage, https://github.com/GabrielF98/fouriersmooth
Project-URL: Issues, https://github.com/GabrielF98/fouriersmooth/issues
Classifier: Programming Language :: Python :: 3
Classifier: License :: OSI Approved :: MIT License
Classifier: Operating System :: OS Independent
Requires-Python: >=3.11
License-File: LICENSE
Requires-Dist: numpy>=1.20
Requires-Dist: scipy>=1.14
Requires-Dist: matplotlib>=3.9
Requires-Dist: pandas>=2.2
Provides-Extra: test
Requires-Dist: pytest==8.3.4; extra == "test"
